vhdl_code/DAC_8831/dac_module.vhdl
library IEEE;
use IEEE.std_logic_1164.all; 

entity DAC_8831_MODULE is 
Port(
    -- System ports
    master_clock : in std_logic;

    -- DAC ports
    ldac : out std_logic := '0';
    chip_select : out std_logic := '1';
    serial_clock : out std_logic := '1';
    sdi : out std_logic := '0';

    -- Ports from processing unit
    data_in : in std_logic_vector(15 downto 0);
    data_in_valid : in std_logic := '0'
);
end DAC_8831_MODULE;

architecture Behavioral of DAC_8831_MODULE is 
    -- Signals with initial values
    signal bit_counter : integer range 0 to 16 := 0;  -- Extended to 16
    signal is_writing : std_logic := '0';
    signal data_buffer : std_logic_vector(15 downto 0) := (others => '0');
    signal data_loaded : std_logic := '0';

    -- Signals related to safety trigger
    signal buffer_time_counter : integer range 0 to 3_000 := 0;
    constant buffer_time_max : integer := 3_000;
begin 
    -- Connect serial clock directly
    serial_clock <= master_clock; 

    -- Single process for all DAC control logic
    DAC_CONTROL: process(master_clock)
    variable start_sync : std_logic_vector(1 downto 0) := "00";
    begin
        if falling_edge(master_clock) then
            -- Default assignments
            ldac <= '0';  -- Typically held low for continuous updates
            start_sync := start_sync(0) & data_in_valid;
            -- Data loading logic
            if start_sync = "01" and is_writing = '0' then
                data_buffer <= data_in;
                data_loaded <= '1';
            end if;
            
            -- Transmission state machine
            if is_writing = '1' then
                -- Actively shifting out data
                if bit_counter < 16 then
                    sdi <= data_buffer(15 - bit_counter);  -- MSB first
                    bit_counter <= bit_counter + 1;
                else
                    -- End of transmission
                    chip_select <= '1';
                    is_writing <= '0';
                    bit_counter <= 0;
                    data_loaded <= '0';
                end if;
            elsif data_loaded = '1' then
                -- Start new transmission
                buffer_time_counter <= 0;
                chip_select <= '0';
                is_writing <= '1';
                bit_counter <= 0;
                -- sdi <= data_buffer(15);  -- First bit
            end if;
            
            -- Block to reset output to 0V if stimulation time is high for too long
            if (data_buffer /= x"8000") then 
                buffer_time_counter <= buffer_time_counter + 1;
                if (buffer_time_counter = buffer_time_max) then 
                    buffer_time_counter <= 0;
                    bit_counter <= 0;
                    data_buffer <= x"8000";
                    data_loaded <= '1';
                end if;
            end if;

        end if;
    end process DAC_CONTROL;
    
end Behavioral;

vhdl_code/DAC8831/dac_testbench.vhdl
library IEEE;
use IEEE.std_logic_1164.all;
use IEEE.numeric_std.all;

entity dac_module_testbench is 
end entity dac_module_testbench;

architecture testbench_arch of dac_module_testbench is

component DAC_8831_MODULE
    Port(
        -- System ports
        master_clock : in std_logic;

        -- DAC ports
        ldac : out std_logic := '0';
        chip_select : out std_logic := '1';
        serial_clock : out std_logic := '1';
        sdi : out std_logic := '0';

        -- Ports from processing unit
        data_in : in std_logic_vector(15 downto 0) := (others => '0');
        data_in_valid : in std_logic := '0'
    );
end component;

--- Ports mimicking DAC_8831
signal dac_ldac : std_logic;
signal dac_cs : std_logic;
signal dac_sclk : std_logic;
signal dac_sdi : std_logic;

--- Ports mimicking inputs from processing unit
signal waveshape_data : std_logic_vector(15 downto 0) := (others => '0');
signal data_ready : std_logic := '0';

-- System signals
signal clock_12MHz : std_logic := '0';
constant clock_12MHz_period : time := 83.333 ns;
signal test_complete : boolean := false;

begin 
    uut: DAC_8831_MODULE
        port map (
            master_clock => clock_12MHz,
            ldac => dac_ldac,
            chip_select => dac_cs,
            serial_clock => dac_sclk,
            sdi => dac_sdi,
            data_in => waveshape_data,
            data_in_valid => data_ready
        );
    
    -- System clock generation 
    clock_12MHz <= not clock_12MHz after clock_12MHz_period/2 when not test_complete else '0';

    stimuli: process 
        begin 
        report("Starting simulation");
        wait for 100 ns;

        waveshape_data <= x"A5A5";
        data_ready <= '1';
        wait for 150 ns;
        data_ready <= '0';
        wait for 1.6 us;

        waveshape_data <= x"AAAA";
        data_ready <= '1';
        wait for 150 ns;
        data_ready <= '0';
        wait for 1.6 us;

        test_complete <= true;
        report("Simulation complete");
        wait;
    end process;

end architecture testbench_arch;

vhdl_code/DAC8831/output_graph.vcd
$date
  Thu Apr 24 23:34:58 2025
$end
$version
  GHDL v0
$end
$timescale
  1 fs
$end
$scope module standard $end
$upscope $end
$scope module std_logic_1164 $end
$upscope $end
$scope module numeric_std $end
$upscope $end
$scope module dac_module_testbench $end
$var reg 1 ! dac_ldac $end
$var reg 1 " dac_cs $end
$var reg 1 # dac_sclk $end
$var reg 1 $ dac_sdi $end
$var reg 16 % waveshape_data[15:0] $end
$var reg 1 & data_ready $end
$var reg 1 ' clock_12mhz $end
$var reg 1 ( test_complete $end
$scope module uut $end
$var reg 1 ) master_clock $end
$var reg 1 * ldac $end
$var reg 1 + chip_select $end
$var reg 1 , serial_clock $end
$var reg 1 - sdi $end
$var reg 16 . data_in[15:0] $end
$var reg 1 / data_in_valid $end
$var integer 32 0 bit_counter $end
$var reg 1 1 is_writing $end
$var reg 16 2 data_buffer[15:0] $end
$var reg 1 3 data_loaded $end
$upscope $end
$upscope $end
$enddefinitions $end
#0
0!
1"
0#
0$
bUUUUUUUUUUUUUUUU %
0&
0'
0(
0)
0*
1+
0,
0-
bUUUUUUUUUUUUUUUU .
0/
b0 0
01
b0000000000000000 2
03
#41666500
1#
1'
1)
1,
#83333000
0#
0'
0)
0,
#100000000
b1010010110100101 %
1&
b1010010110100101 .
1/
#124999500
1#
1'
1)
1,
#166666000
0#
0'
0)
0,
b1010010110100101 2
13
#208332500
1#
1'
1)
1,
#249999000
0"
0#
0'
0)
0+
0,
11
#250000000
0&
0/
#291665500
1#
1'
1)
1,
#333332000
0#
1$
0'
0)
0,
1-
b1 0
#374998500
1#
1'
1)
1,
#416665000
0#
0$
0'
0)
0,
0-
b10 0
#458331500
1#
1'
1)
1,
#499998000
0#
1$
0'
0)
0,
1-
b11 0
#541664500
1#
1'
1)
1,
#583331000
0#
0$
0'
0)
0,
0-
b100 0
#624997500
1#
1'
1)
1,
#666664000
0#
0'
0)
0,
b101 0
#708330500
1#
1'
1)
1,
#749997000
0#
1$
0'
0)
0,
1-
b110 0
#791663500
1#
1'
1)
1,
#833330000
0#
0$
0'
0)
0,
0-
b111 0
#874996500
1#
1'
1)
1,
#916663000
0#
1$
0'
0)
0,
1-
b1000 0
#958329500
1#
1'
1)
1,
#999996000
0#
0'
0)
0,
b1001 0
#1041662500
1#
1'
1)
1,
#1083329000
0#
0$
0'
0)
0,
0-
b1010 0
#1124995500
1#
1'
1)
1,
#1166662000
0#
1$
0'
0)
0,
1-
b1011 0
#1208328500
1#
1'
1)
1,
#1249995000
0#
0$
0'
0)
0,
0-
b1100 0
#1291661500
1#
1'
1)
1,
#1333328000
0#
0'
0)
0,
b1101 0
#1374994500
1#
1'
1)
1,
#1416661000
0#
1$
0'
0)
0,
1-
b1110 0
#1458327500
1#
1'
1)
1,
#1499994000
0#
0$
0'
0)
0,
0-
b1111 0
#1541660500
1#
1'
1)
1,
#1583327000
0#
1$
0'
0)
0,
1-
b10000 0
#1624993500
1#
1'
1)
1,
#1666660000
1"
0#
0'
0)
1+
0,
b0 0
01
03
#1708326500
1#
1'
1)
1,
#1749993000
0#
0'
0)
0,
#1791659500
1#
1'
1)
1,
#1833326000
0#
0'
0)
0,
#1850000000
b1010101010101010 %
1&
b1010101010101010 .
1/
#1874992500
1#
1'
1)
1,
#1916659000
0#
0'
0)
0,
b1010101010101010 2
13
#1958325500
1#
1'
1)
1,
#1999992000
0"
0#
0'
0)
0+
0,
11
#2000000000
0&
0/
#2041658500
1#
1'
1)
1,
#2083325000
0#
0'
0)
0,
b1 0
#2124991500
1#
1'
1)
1,
#2166658000
0#
0$
0'
0)
0,
0-
b10 0
#2208324500
1#
1'
1)
1,
#2249991000
0#
1$
0'
0)
0,
1-
b11 0
#2291657500
1#
1'
1)
1,
#2333324000
0#
0$
0'
0)
0,
0-
b100 0
#2374990500
1#
1'
1)
1,
#2416657000
0#
1$
0'
0)
0,
1-
b101 0
#2458323500
1#
1'
1)
1,
#2499990000
0#
0$
0'
0)
0,
0-
b110 0
#2541656500
1#
1'
1)
1,
#2583323000
0#
1$
0'
0)
0,
1-
b111 0
#2624989500
1#
1'
1)
1,
#2666656000
0#
0$
0'
0)
0,
0-
b1000 0
#2708322500
1#
1'
1)
1,
#2749989000
0#
1$
0'
0)
0,
1-
b1001 0
#2791655500
1#
1'
1)
1,
#2833322000
0#
0$
0'
0)
0,
0-
b1010 0
#2874988500
1#
1'
1)
1,
#2916655000
0#
1$
0'
0)
0,
1-
b1011 0
#2958321500
1#
1'
1)
1,
#2999988000
0#
0$
0'
0)
0,
0-
b1100 0
#3041654500
1#
1'
1)
1,
#3083321000
0#
1$
0'
0)
0,
1-
b1101 0
#3124987500
1#
1'
1)
1,
#3166654000
0#
0$
0'
0)
0,
0-
b1110 0
#3208320500
1#
1'
1)
1,
#3249987000
0#
1$
0'
0)
0,
1-
b1111 0
#3291653500
1#
1'
1)
1,
#3333320000
0#
0$
0'
0)
0,
0-
b10000 0
#3374986500
1#
1'
1)
1,
#3416653000
1"
0#
0'
0)
1+
0,
b0 0
01
03
#3458319500
1#
1'
1)
1,
#3499986000
0#
0'
0)
0,
#3541652500
1#
1'
1)
1,
#3583319000
0#
0'
0)
0,
#3600000000
1(
